streamlit_gtag/__init__.py
streamlit_gtag/frontend/index.html
streamlit_gtag/frontend/main.js
streamlit_gtag/frontend/streamlit-component-lib.js
streamlit_google_analytics_tag-1.1.dist-info/METADATA
streamlit_google_analytics_tag-1.1.dist-info/WHEEL
streamlit_google_analytics_tag-1.1.dist-info/top_level.txt
streamlit_google_analytics_tag-1.1.dist-info/RECORD
